doc/conf.py
dotbot/__init__.py
dotbot/adapter.py
dotbot/calibration_exporter.py
dotbot/controller.py
dotbot/controller_app.py
dotbot/dotbot_simulator.py
dotbot/hdlc.py
dotbot/joystick.py
dotbot/keyboard.py
dotbot/lighthouse2.py
dotbot/logger.py
dotbot/models.py
dotbot/protocol.py
dotbot/rest.py
dotbot/sailbot_simulator.py
dotbot/serial_interface.py
dotbot/server.py
dotbot/frontend/.env
dotbot/frontend/.env.example
dotbot/frontend/.env.test
dotbot/frontend/.gitignore
dotbot/frontend/config-overrides.js
dotbot/frontend/package-lock.json
dotbot/frontend/package.json
dotbot/frontend/build/asset-manifest.json
dotbot/frontend/build/index.html
dotbot/frontend/build/manifest.json
dotbot/frontend/build/robots.txt
dotbot/frontend/build/static/css/main.bc44462f.css
dotbot/frontend/build/static/css/main.bc44462f.css.map
dotbot/frontend/build/static/js/main.70e53fd3.js
dotbot/frontend/build/static/js/main.70e53fd3.js.LICENSE.txt
dotbot/frontend/build/static/js/main.70e53fd3.js.map
dotbot/frontend/build/static/media/bootstrap-icons.39795c0b4513de014cf8.woff
dotbot/frontend/build/static/media/bootstrap-icons.b7bcc075b395c14ce8c2.woff2
dotbot/frontend/public/index.html
dotbot/frontend/public/manifest.json
dotbot/frontend/public/robots.txt
dotbot/frontend/src/App.js
dotbot/frontend/src/DotBotItem.js
dotbot/frontend/src/DotBots.js
dotbot/frontend/src/DotBots.test.js
dotbot/frontend/src/DotBotsMap.js
dotbot/frontend/src/Joystick.js
dotbot/frontend/src/Joystick.test.js
dotbot/frontend/src/QrKeyForm.css
dotbot/frontend/src/QrKeyForm.js
dotbot/frontend/src/SailBotItem.js
dotbot/frontend/src/SailBotsMap.js
dotbot/frontend/src/XGOItem.js
dotbot/frontend/src/index.js
dotbot/frontend/src/hooks/keyPress.js
dotbot/frontend/src/utils/constants.js
dotbot/frontend/src/utils/helpers.js
dotbot/frontend/src/utils/logger.js
dotbot/lib/.gitignore
dotbot/lib/CMakeLists.txt
dotbot/lib/lh2.c
dotbot/lib/lh2.so
dotbot/lib/_build/.ninja_deps
pydotbot-0.26.0.dist-info/METADATA
pydotbot-0.26.0.dist-info/WHEEL
pydotbot-0.26.0.dist-info/entry_points.txt
pydotbot-0.26.0.dist-info/RECORD
pydotbot-0.26.0.dist-info/licenses/AUTHORS
pydotbot-0.26.0.dist-info/licenses/LICENSE.txt
