Metadata-Version: 2.4
Name: pydotbot
Version: 0.26.0
Summary: Package to easily control your DotBots and SailBots.
Project-URL: Homepage, https://github.com/DotBots/PyDotBot
Project-URL: Bug Tracker, https://github.com/DotBots/PyDotBot/issues
Author-email: Alexandre Abadie <alexandre.abadie@inria.fr>, Theo Akbas <theo.akbas@inria.fr>, Filip Maksimovic <filip.maksimovic@inria.fr>, Said Alvarado-Marin <said-alexander.alvarado-marin@inria.fr>, Mališa Vučinić <malisa.vucinic@inria.fr>, Diego Badillo <diego.badillo@sansano.usm.cl>
License: BSD
License-File: AUTHORS
License-File: LICENSE.txt
Classifier: License :: OSI Approved :: BSD License
Classifier: Operating System :: MacOS
Classifier: Operating System :: Microsoft :: Windows
Classifier: Operating System :: POSIX :: Linux
Classifier: Programming Language :: C
Classifier: Programming Language :: Python :: 3
Requires-Python: >=3.7
Requires-Dist: click>=8.1.7
Requires-Dist: fastapi>=0.115.0
Requires-Dist: gmqtt>=0.7.0
Requires-Dist: haversine>=2.8.0
Requires-Dist: httpx>=0.27.2
Requires-Dist: marilib-pkg>=0.7.1
Requires-Dist: numpy>=2.1.1
Requires-Dist: opencv-python>=4.12.0.88
Requires-Dist: pygame>=2.6.1
Requires-Dist: pynput>=1.7.6
Requires-Dist: pyserial>=3.5
Requires-Dist: qrkey==0.9.1
Requires-Dist: structlog>=24.4.0
Requires-Dist: uvicorn>=0.32.0
Requires-Dist: websockets>=13.1.0
